xkits_lib/__init__.py
xkits_lib/annot.py
xkits_lib/attribute.py
xkits_lib/cache.py
xkits_lib/meter.py
xkits_lib/path.py
xkits_lib/time.py
xkits_lib/unit.py
xkits_lib/utils.py
xkits_lib-0.4.dist-info/LICENSE
xkits_lib-0.4.dist-info/METADATA
xkits_lib-0.4.dist-info/WHEEL
xkits_lib-0.4.dist-info/top_level.txt
xkits_lib-0.4.dist-info/zip-safe
xkits_lib-0.4.dist-info/RECORD
