Metadata-Version: 2.1
Name: xkits-lib
Version: 0.4
Summary: Common library
Home-page: https://github.com/bondbox/xlibrary/
Author: Mingzhe Zou
Author-email: zoumingzhe@outlook.com
License: GPLv2
Project-URL: Source Code, https://github.com/bondbox/xlibrary/
Project-URL: Bug Tracker, https://github.com/bondbox/xlibrary/issues
Project-URL: Documentation, https://github.com/bondbox/xlibrary/
Keywords: library
Platform: any
Classifier: Programming Language :: Python
Classifier: Programming Language :: Python :: 3
Requires-Python: >=3.8
License-File: LICENSE
